{
    "title": "Questions for Jeremy Dan",
    "date": "2026-07-16",
    "excerpt": "Do you remember your childhood dreams? i wanted to drive nascar",
    "image": "",
    "format": "qa",
    "body": "Do you remember your childhood dreams?\ni wanted to drive nascar\n\nMorning shower or evening?\nmorning\n\nIs there anything you regret not doing?\nbeing more selfish, not kissing a few girls, keeping more money, not punching some dudes in the mouth\nalso not going to the fucking gym\nnot folding AQo when i got 3 bet utg v gun2 by the only competent player at my table table 12 left of the monster stack prob cost me a half mil. four betting him was fucking retarded i need to learn how to go slower\noh, and losing that 25k chip at the fucking encore after i got second in the 25k. what the fuck man\n\nWhat was your first job?\n$5 shoe warehouse, bensonhurst\n\nWhat would you put on your tombstone?\ni would let chandler write it, i would probably write some bullshit about living or dying by the sword, but I don't think I know my truth as well as the people I love.\n\nWhat would be your last meal?\ntacis beyti lamb chops + kunefe + spinach pie\n\nWhat are you reading?\nchatgpt telling me everything is going to be ok\n\nWhat movie have you seen the most times?\nmean girls on the bus in camp\n\nThoughts on love?\ni think it's the driving force behind everything, but I dunno, i think when you know you know and i don't\n\nWhat are your beauty secrets?\nbe vulgar and aggressive\n\nHow do you know when you've had enough?\nwhen i can't look myself in the eyes\n\nWhen do you get nervous?\nWhen I sit still\n\nWhat's living on your nightstand?\nwhite claw that a girl never finished, maybe she'll come back, nasal strips, cologne, she never liked me anyways, lamp i never use, remote for a TV i don't use, i should text her\n\nFavorite thing about the city you live in?\nIt is infinite\n\nHave you been kicked out anywhere?\ndrais when the grinder won the main event. a frat basement in school because they thought i was a different white boy, a group chat where me and some homies played mafia and board games a couple years ago for no real reason that still bums me out\n\nWhat keeps you here?\nI kind of just hate myself and everything about and around me so I think I can fix that and then see what's good. Also I wanna be up there with the best in the world at whatever I do. I dunno. I'm a fucking loser\nThere's always another mountain and things will always get better\nOne of my ogs told me once that I haven't come close to being the end product of myself a couple years ago. That I have no idea how many lifetimes I've yet to live. I cling to it"
}
